delpha_mcp/__init__.py
delpha_mcp/__main__.py
delpha_mcp/client.py
delpha_mcp/config.py
delpha_mcp/server.py
delpha_mcp-0.1.19.dist-info/licenses/LICENSE
delpha_mcp-0.1.19.dist-info/METADATA
delpha_mcp-0.1.19.dist-info/WHEEL
delpha_mcp-0.1.19.dist-info/entry_points.txt
delpha_mcp-0.1.19.dist-info/top_level.txt
delpha_mcp-0.1.19.dist-info/RECORD
