Metadata-Version: 2.4
Name: delpha-mcp
Version: 0.1.19
Summary: Intelligent AI Agents to ensure accurate, unique, and reliable customer data
Author-email: Victor Goubet <support.api@delpha.io>
Maintainer-email: Delpha <support.api@delpha.io>
License-Expression: MIT
Project-URL: Homepage, https://github.com/Delpha-Assistant/DelphaMCP
Project-URL: Documentation, https://github.com/Delpha-Assistant/DelphaMCP#readme
Project-URL: Issues, https://github.com/Delpha-Assistant/DelphaMCP/issues
Keywords: data quality,validation,MCP,AI,delpha,email,email finder,email validator,address,name,social,phone,website,legal id
Classifier: Programming Language :: Python :: 3
Classifier: Programming Language :: Python :: 3.8
Classifier: Programming Language :: Python :: 3.9
Classifier: Programming Language :: Python :: 3.10
Classifier: Programming Language :: Python :: 3.11
Classifier: Operating System :: OS Independent
Classifier: Intended Audience :: Developers
Classifier: Development Status :: 4 - Beta
Classifier: Topic :: Software Development :: Libraries :: Application Frameworks
Requires-Python: >=3.8
License-File: LICENSE
Requires-Dist: fastmcp>=0.1.0
Requires-Dist: httpx>=0.25.0
Requires-Dist: pydantic>=2.0.0
Requires-Dist: pydantic-settings>=2.0.0
Requires-Dist: python-dotenv>=1.0.0
Requires-Dist: authlib>=1.2.0
Provides-Extra: dev
Requires-Dist: ruff>=0.4.0; extra == "dev"
Requires-Dist: pytest>=7.0.0; extra == "dev"
Requires-Dist: build; extra == "dev"
Dynamic: license-file
